accounts/__init__.py
accounts/admin.py
accounts/apps.py
accounts/signals.py
accounts/urls.py
accounts/filters/__init__.py
accounts/filters/user.py
accounts/migrations/0001_initial.py
accounts/migrations/__init__.py
accounts/models/__init__.py
accounts/models/choices.py
accounts/models/laboratory.py
accounts/models/laboratory_membership.py
accounts/models/profile.py
accounts/models/user.py
accounts/serializers/__init__.py
accounts/serializers/group.py
accounts/serializers/laboratory.py
accounts/serializers/profile.py
accounts/serializers/user.py
accounts/tests/__init__.py
accounts/tests/factories.py
accounts/tests/test_admin.py
accounts/tests/test_backends.py
accounts/tests/test_models.py
accounts/tests/utils.py
accounts/views/__init__.py
accounts/views/group.py
accounts/views/laboratory.py
accounts/views/profile.py
accounts/views/user.py
pylabber/__init__.py
pylabber/settings.py
pylabber/test_settings.py
pylabber/urls.py
pylabber/wsgi.py
pylabber/utils/__init__.py
pylabber/utils/utils.py
pylabber-0.1.0.data/scripts/manage.py
research/__init__.py
research/admin.py
research/apps.py
research/urls.py
research/filters/__init__.py
research/filters/group_filter.py
research/filters/subject_filter.py
research/migrations/0001_initial.py
research/migrations/__init__.py
research/models/__init__.py
research/models/choices.py
research/models/group.py
research/models/study.py
research/models/subject.py
research/models/validators.py
research/serializers/__init__.py
research/serializers/group.py
research/serializers/study.py
research/serializers/subject.py
research/tests/__init__.py
research/tests/factories.py
research/tests/test_app_config.py
research/tests/test_models.py
research/tests/test_views.py
research/utils/__init__.py
research/utils/custom_attributes_processor.py
research/utils/get_subject_model.py
research/utils/subject_table.py
research/views/__init__.py
research/views/group.py
research/views/study.py
research/views/subject.py
utils/__init__.py
utils/handle_interrupt.py
pylabber-0.1.0.dist-info/LICENSE
pylabber-0.1.0.dist-info/METADATA
pylabber-0.1.0.dist-info/WHEEL
pylabber-0.1.0.dist-info/dependency_links.txt
pylabber-0.1.0.dist-info/top_level.txt
pylabber-0.1.0.dist-info/RECORD
