Metadata-Version: 2.1
Name: pylabber
Version: 0.1.0
Summary: A Django app to manage neuroscience research
Home-page: https://github.com/TheLabbingProject/pylabber
Author: Zvi Baratz
Author-email: baratzz@pm.me
License: AGPLv3
Keywords: django research neuroscience
Platform: UNKNOWN
Classifier: Development Status :: 3 - Alpha
Classifier: Environment :: Web Environment
Classifier: Framework :: Django :: 3.0
Classifier: Intended Audience :: Science/Research
Classifier: License :: OSI Approved :: GNU Affero General Public License v3
Classifier: Operating System :: OS Independent
Classifier: Programming Language :: Python :: 3.7
Classifier: Programming Language :: Python :: 3.8
Requires-Python: >=3.6
Requires-Dist: bokeh (~=2.0)
Requires-Dist: bs4 (~=0.0)
Requires-Dist: Django (==3.*)
Requires-Dist: djangorestframework (~=3.11)
Requires-Dist: djangorestframework-camel-case (~=1.1)
Requires-Dist: django-cors-headers (~=3.2)
Requires-Dist: django-environ (~=0.4)
Requires-Dist: django-model-utils (==4.*)
Requires-Dist: django-rest-auth (~=0.9)
Requires-Dist: django-extensions (~=2.2)
Requires-Dist: django-filter (~=2.2)
Requires-Dist: nipype (~=1.5)
Requires-Dist: numpy (~=1.19)
Requires-Dist: pandas (~=0.25)
Requires-Dist: Pillow (~=6.2)
Requires-Dist: psycopg2-binary (~=2.8)
Requires-Dist: xlrd (~=1.2)
Provides-Extra: dev
Requires-Dist: black (==19.10b0) ; extra == 'dev'
Requires-Dist: coverage (~=4.5) ; extra == 'dev'
Requires-Dist: factory-boy (~=2.12) ; extra == 'dev'
Requires-Dist: flake8 (~=3.7) ; extra == 'dev'
Requires-Dist: ipython (~=7.10) ; extra == 'dev'
Requires-Dist: pytest (~=5.3) ; extra == 'dev'
Requires-Dist: sphinx (~=2.2) ; extra == 'dev'
Requires-Dist: sphinx-rtd-theme (~=0.4) ; extra == 'dev'
